st_click_detector/__init__.py
st_click_detector/frontend/build/asset-manifest.json
st_click_detector/frontend/build/bootstrap.min.css
st_click_detector/frontend/build/index.html
st_click_detector/frontend/build/precache-manifest.02e379f751fc2430c952c42e4c59ce38.js
st_click_detector/frontend/build/precache-manifest.13e6b5e7516ca97028e839bb839d635d.js
st_click_detector/frontend/build/precache-manifest.213a639ffb129b3691f693d0ed36a3af.js
st_click_detector/frontend/build/precache-manifest.29168824f89d1d8c03c2960880896991.js
st_click_detector/frontend/build/precache-manifest.5b688bec555b037e09294c0889a3d460.js
st_click_detector/frontend/build/precache-manifest.615aef389dc4f018d1a37f0a885c9b6b.js
st_click_detector/frontend/build/precache-manifest.6a1a75ab2038f8ce4f98880c6fa301d5.js
st_click_detector/frontend/build/precache-manifest.7812577f73af524227cd507b61ecb90c.js
st_click_detector/frontend/build/precache-manifest.7977705a915ad9e3425137f1aa4828c6.js
st_click_detector/frontend/build/precache-manifest.79fe7e1cbde6cfebaacdfe97c2658549.js
st_click_detector/frontend/build/precache-manifest.a7163370985678fff0f9b109a3862524.js
st_click_detector/frontend/build/precache-manifest.b030b95b9f0a42106848298268985f5d.js
st_click_detector/frontend/build/precache-manifest.d6b07089b2b67f0e046bac9b4282091f.js
st_click_detector/frontend/build/precache-manifest.da0f4f64d929196ef3e351235924e043.js
st_click_detector/frontend/build/precache-manifest.dadc25f35877b898d86bb8a64616b250.js
st_click_detector/frontend/build/precache-manifest.f27c6cdad180752546bff31162e6e21f.js
st_click_detector/frontend/build/service-worker.js
st_click_detector/frontend/build/static/js/2.e5a21520.chunk.js
st_click_detector/frontend/build/static/js/2.e5a21520.chunk.js.LICENSE.txt
st_click_detector/frontend/build/static/js/2.e5a21520.chunk.js.map
st_click_detector/frontend/build/static/js/2.ef58ee94.chunk.js
st_click_detector/frontend/build/static/js/2.ef58ee94.chunk.js.LICENSE.txt
st_click_detector_fix-0.1.7.dist-info/LICENSE
st_click_detector_fix-0.1.7.dist-info/METADATA
st_click_detector_fix-0.1.7.dist-info/WHEEL
st_click_detector_fix-0.1.7.dist-info/top_level.txt
st_click_detector_fix-0.1.7.dist-info/RECORD
