Metadata-Version: 2.1
Name: st-click-detector-fix
Version: 0.1.7
Summary: A Streamlit component to detect clicks
Home-page: 
Author: 
Author-email: 
Requires-Python: >=3.6
License-File: LICENSE
Requires-Dist: streamlit >=0.63
